bandu/abinit_reader.py
bandu/bandu.py
bandu/brillouin_zone.py
bandu/colors.py
bandu/isosurface_class.py
bandu/plotter.py
bandu/translate.py
bandu/wfk_class.py
bandu/xsf_reader.py
bandu-1.3.6.dist-info/licenses/LICENSE
bandu-1.3.6.dist-info/METADATA
bandu-1.3.6.dist-info/WHEEL
bandu-1.3.6.dist-info/top_level.txt
bandu-1.3.6.dist-info/RECORD
