Metadata-Version: 2.4
Name: bandu
Version: 1.3.6
Summary: The BandU program constructs a rank ordered series of crystal orbitals using principal component analysis. These principal orbital components can then be projected on the Fermi surface and visualized
Author-email: Patrick Cross <pcross@wisc.edu>
Project-URL: Homepage, https://github.com/pcross0405/BandU
Project-URL: Issues, https://github.com/pcross0405/BandU/issues
Classifier: Programming Language :: Python :: 3
Classifier: License :: OSI Approved :: MIT License
Classifier: Operating System :: OS Independent
Requires-Python: >=3.11
License-File: LICENSE
Dynamic: license-file
